quri_parts/pyscf/NOTICE
quri_parts/pyscf/__init__.py
quri_parts/pyscf/mol/__init__.py
quri_parts/pyscf/mol/model.py
quri_parts/pyscf/mol/non_relativistic.py
quri_parts/pyscf/py.typed
quri_parts_pyscf-17.0.0.dist-info/LICENSE
quri_parts_pyscf-17.0.0.dist-info/METADATA
quri_parts_pyscf-17.0.0.dist-info/WHEEL
quri_parts_pyscf-17.0.0.dist-info/RECORD
