Metadata-Version: 2.1
Name: quri-parts-pyscf
Version: 17.0.0
Summary: A plugin to use PySCF with QURI Parts
Home-page: https://github.com/QunaSys/quri-parts
License: Apache-2.0
Keywords: quantum,quantum computing
Author: QURI Parts Authors
Author-email: opensource@qunasys.com
Requires-Python: >=3.9.8,<4.0.0
Classifier: License :: OSI Approved :: Apache Software License
Classifier: Programming Language :: Python :: 3
Classifier: Programming Language :: Python :: 3.10
Classifier: Programming Language :: Python :: 3.11
Classifier: Topic :: Scientific/Engineering :: Physics
Classifier: Typing :: Typed
Requires-Dist: numpy (>=1.22.0)
Requires-Dist: pyscf (>=2.3.0,<3.0.0)
Requires-Dist: quri-parts-chem
Requires-Dist: quri-parts-core
Requires-Dist: typing-extensions (>=4.1.1,<5.0.0)
Project-URL: Documentation, https://quri-parts.qunasys.com
Project-URL: Repository, https://github.com/QunaSys/quri-parts
